debiased_spatial_whittle/__init__.py
debiased_spatial_whittle/backend.py
debiased_spatial_whittle/france.jpg
debiased_spatial_whittle/grids/__init__.py
debiased_spatial_whittle/grids/base.py
debiased_spatial_whittle/grids/old.py
debiased_spatial_whittle/grids/spatial_kernel.py
debiased_spatial_whittle/inference/__init__.py
debiased_spatial_whittle/inference/confidence.py
debiased_spatial_whittle/inference/diagnostics.py
debiased_spatial_whittle/inference/hypothesis_tests.py
debiased_spatial_whittle/inference/least_squares.py
debiased_spatial_whittle/inference/likelihood.py
debiased_spatial_whittle/inference/multivariate_periodogram.py
debiased_spatial_whittle/inference/old.py
debiased_spatial_whittle/inference/periodogram.py
debiased_spatial_whittle/models/__init__.py
debiased_spatial_whittle/models/base.py
debiased_spatial_whittle/models/bivariate.py
debiased_spatial_whittle/models/old.py
debiased_spatial_whittle/models/spectral.py
debiased_spatial_whittle/models/univariate.py
debiased_spatial_whittle/sampling/__init__.py
debiased_spatial_whittle/sampling/old.py
debiased_spatial_whittle/sampling/samples.py
debiased_spatial_whittle/sampling/simulation.py
debiased_spatial_whittle/utils.py
debiased_spatial_whittle-2.1.2.dist-info/LICENSE
debiased_spatial_whittle-2.1.2.dist-info/WHEEL
debiased_spatial_whittle-2.1.2.dist-info/METADATA
debiased_spatial_whittle-2.1.2.dist-info/RECORD
