Metadata-Version: 2.1
Name: debiased-spatial-whittle
Version: 2.1.2
Summary: Spatial Debiased Whittle likelihood for fast inference of spatio-temporal covariance models from gridded data
Home-page: http://arthurpgb.pythonanywhere.com/sdw
Keywords: random fields,statistics,whittle,spatial,matern,kriging,interpolation
Author: arthur
Author-email: ahw795@qmul.ac.uk
Requires-Python: >=3.9,<4.0
Classifier: Programming Language :: Python :: 3
Classifier: Programming Language :: Python :: 3.9
Classifier: Programming Language :: Python :: 3.10
Classifier: Programming Language :: Python :: 3.11
Provides-Extra: gpu11
Provides-Extra: gpu12
Requires-Dist: autograd (>=1.5,<2.0)
Requires-Dist: cupy-cuda11x ; extra == "gpu11"
Requires-Dist: cupy-cuda12x (>=13.0.0,<14.0.0) ; extra == "gpu12"
Requires-Dist: matplotlib (>=3.7.0,<4.0.0)
Requires-Dist: numpy (>=1.21.5,<2.0.0)
Requires-Dist: param (>=2.1.1,<3.0.0)
Requires-Dist: progressbar2 (>=4.2.0,<5.0.0)
Requires-Dist: pytest-cov (>=6.2.1,<7.0.0)
Requires-Dist: scipy (>=1.7.3,<2.0.0)
Requires-Dist: seaborn (>=0.12.2,<0.13.0)
Requires-Dist: torch (==2.2.2) ; extra == "gpu12" or extra == "gpu11"
